normalize_folder_name/__init__.py
normalize_folder_name/normalized_folder_name_cli.py
sigaocaue_normalize_folder_name-0.1.1.dist-info/METADATA
sigaocaue_normalize_folder_name-0.1.1.dist-info/WHEEL
sigaocaue_normalize_folder_name-0.1.1.dist-info/entry_points.txt
sigaocaue_normalize_folder_name-0.1.1.dist-info/top_level.txt
sigaocaue_normalize_folder_name-0.1.1.dist-info/RECORD
