Metadata-Version: 2.1
Name: sigaocaue_normalize_folder_name
Version: 0.1.1
Summary: O Normalize Folder Name CLI é uma ferramenta de linha de comando desenvolvida para auxiliar
Home-page: https://github.com/sigaocaue/normalize_folder_name
Author: Cauê Prado
Author-email: caue.prado0@gmail.com
Classifier: Programming Language :: Python :: 3
Classifier: License :: OSI Approved :: MIT License
Classifier: Operating System :: OS Independent
Requires-Python: >=3.6
Requires-Dist: click >=7.0
Requires-Dist: unidecode >=1.1.1
Requires-Dist: gnureadline >=6.3 ; platform_system == "Darwin"
Requires-Dist: pyreadline >=2.1 ; platform_system == "Windows"
